datascizer/__init__.py
datascizer/tests/__init__.py
datascizer-0.1.0.dist-info/LICENSE
datascizer-0.1.0.dist-info/METADATA
datascizer-0.1.0.dist-info/WHEEL
datascizer-0.1.0.dist-info/top_level.txt
datascizer-0.1.0.dist-info/RECORD
